gistbin/__init__.py
gistbin/lib.py
gistbin-0.5.0.data/scripts/gistbin
gistbin-0.5.0.dist-info/LICENSE
gistbin-0.5.0.dist-info/METADATA
gistbin-0.5.0.dist-info/WHEEL
gistbin-0.5.0.dist-info/top_level.txt
gistbin-0.5.0.dist-info/RECORD
