Metadata-Version: 2.1
Name: gistbin
Version: 0.5.0
Summary: Github Gist client allowing for quick uploads via commandline.
Home-page: https://gistbin.chand1012.dev/
Author: Chandler Lofland (chand1012)
Author-email: business@chand1012.net
License: UNKNOWN
Platform: UNKNOWN
Classifier: Programming Language :: Python :: 3
Classifier: License :: OSI Approved :: MIT License
Classifier: Operating System :: OS Independent
Requires-Python: >=3.6
Requires-Dist: requests (>=2.24.0)
Requires-Dist: RandomWords (>=0.3.0)
